// class version 63.0 (63)
// access flags 0x21
public class qua/Quadratic {

  // compiled from: Quadratic.java
  // access flags 0x19
  public final static INNERCLASS java/lang/invoke/MethodHandles$Lookup java/lang/invoke/MethodHandles Lookup

  // access flags 0x1A
  private final static D ERROR = 1.0E-8

  // access flags 0x1
  public <init>()V
   L0
    LINENUMBER 5 L0
    ALOAD 0
    INVOKESPECIAL java/lang/Object.<init> ()V
    RETURN
    MAXSTACK = 1
    MAXLOCALS = 1

  // access flags 0x9
  public static solveQuadratic(DDD)V throws qua/NotEnoughPrecisionException 
   L0
    LINENUMBER 15 L0
    DLOAD 2
    DLOAD 2
    DMUL
    LDC 4.0
    DLOAD 0
    DMUL
    DLOAD 4
    DMUL
    DSUB
    DSTORE 10
   L1
    LINENUMBER 19 L1
    DLOAD 10
    INVOKESTATIC java/lang/Double.isNaN (D)Z
    IFNE L2
    DLOAD 10
    DLOAD 2
    DLOAD 2
    DMUL
    DCMPL
    IFNE L3
   L2
    LINENUMBER 20 L2
   FRAME FULL [D D D T T T T D] []
    NEW qua/NotEnoughPrecisionException
    DUP
    INVOKESPECIAL qua/NotEnoughPrecisionException.<init> ()V
    ATHROW
   L3
    LINENUMBER 23 L3
   FRAME FULL [D D D T T T T D] []
    DLOAD 10
    DCONST_0
    DCMPG
    IFGE L4
   L5
    LINENUMBER 24 L5
    LDC -1.0
    DLOAD 10
    DMUL
    INVOKESTATIC qua/Quadratic.sqrtByNewton (D)D
    DSTORE 6
   L6
    LINENUMBER 25 L6
    LDC -1.0
    DLOAD 2
    DMUL
    LDC 2.0
    DLOAD 0
    DMUL
    DDIV
    INVOKESTATIC qua/Quadratic.formatDouble (D)Ljava/lang/String;
    ASTORE 12
   L7
    LINENUMBER 26 L7
    DLOAD 6
    LDC 2.0
    DLOAD 0
    DMUL
    DDIV
    INVOKESTATIC qua/Quadratic.formatDouble (D)Ljava/lang/String;
    ASTORE 13
   L8
    LINENUMBER 28 L8
    LDC "x1 = "
    ASTORE 14
   L9
    LINENUMBER 29 L9
    ALOAD 14
    ALOAD 12
    LDC "0"
    INVOKEVIRTUAL java/lang/String.equals (Ljava/lang/Object;)Z
    IFNE L10
    ALOAD 12
    INVOKEDYNAMIC makeConcatWithConstants(Ljava/lang/String;)Ljava/lang/String; [
      // handle kind 0x6 : INVOKESTATIC
      java/lang/invoke/StringConcatFactory.makeConcatWithConstants(Ljava/lang/invoke/MethodHandles$Lookup;Ljava/lang/String;Ljava/lang/invoke/MethodType;Ljava/lang/String;[Ljava/lang/Object;)Ljava/lang/invoke/CallSite;
      // arguments:
      "\u0001 + "
    ]
    GOTO L11
   L10
   FRAME FULL [D D D D T T D java/lang/String java/lang/String java/lang/String] [java/lang/String]
    LDC ""
   L11
   FRAME FULL [D D D D T T D java/lang/String java/lang/String java/lang/String] [java/lang/String java/lang/String]
    INVOKEDYNAMIC makeConcatWithConstants(Ljava/lang/String;Ljava/lang/String;)Ljava/lang/String; [
      // handle kind 0x6 : INVOKESTATIC
      java/lang/invoke/StringConcatFactory.makeConcatWithConstants(Ljava/lang/invoke/MethodHandles$Lookup;Ljava/lang/String;Ljava/lang/invoke/MethodType;Ljava/lang/String;[Ljava/lang/Object;)Ljava/lang/invoke/CallSite;
      // arguments:
      "\u0001\u0001"
    ]
    ASTORE 14
   L12
    LINENUMBER 30 L12
    ALOAD 14
    ALOAD 13
    LDC "1"
    INVOKEVIRTUAL java/lang/String.equals (Ljava/lang/Object;)Z
    IFNE L13
    ALOAD 13
    GOTO L14
   L13
   FRAME FULL [D D D D T T D java/lang/String java/lang/String java/lang/String] [java/lang/String]
    LDC ""
   L14
   FRAME FULL [D D D D T T D java/lang/String java/lang/String java/lang/String] [java/lang/String java/lang/String]
    INVOKEDYNAMIC makeConcatWithConstants(Ljava/lang/String;Ljava/lang/String;)Ljava/lang/String; [
      // handle kind 0x6 : INVOKESTATIC
      java/lang/invoke/StringConcatFactory.makeConcatWithConstants(Ljava/lang/invoke/MethodHandles$Lookup;Ljava/lang/String;Ljava/lang/invoke/MethodType;Ljava/lang/String;[Ljava/lang/Object;)Ljava/lang/invoke/CallSite;
      // arguments:
      "\u0001\u0001"
    ]
    ASTORE 14
   L15
    LINENUMBER 31 L15
    ALOAD 14
    INVOKEDYNAMIC makeConcatWithConstants(Ljava/lang/String;)Ljava/lang/String; [
      // handle kind 0x6 : INVOKESTATIC
      java/lang/invoke/StringConcatFactory.makeConcatWithConstants(Ljava/lang/invoke/MethodHandles$Lookup;Ljava/lang/String;Ljava/lang/invoke/MethodType;Ljava/lang/String;[Ljava/lang/Object;)Ljava/lang/invoke/CallSite;
      // arguments:
      "\u0001i\nx2 = "
    ]
    ASTORE 14
   L16
    LINENUMBER 32 L16
    ALOAD 14
    ALOAD 12
    LDC "0"
    INVOKEVIRTUAL java/lang/String.equals (Ljava/lang/Object;)Z
    IFNE L17
    ALOAD 12
    INVOKEDYNAMIC makeConcatWithConstants(Ljava/lang/String;)Ljava/lang/String; [
      // handle kind 0x6 : INVOKESTATIC
      java/lang/invoke/StringConcatFactory.makeConcatWithConstants(Ljava/lang/invoke/MethodHandles$Lookup;Ljava/lang/String;Ljava/lang/invoke/MethodType;Ljava/lang/String;[Ljava/lang/Object;)Ljava/lang/invoke/CallSite;
      // arguments:
      "\u0001 - "
    ]
    GOTO L18
   L17
   FRAME FULL [D D D D T T D java/lang/String java/lang/String java/lang/String] [java/lang/String]
    LDC "-"
   L18
   FRAME FULL [D D D D T T D java/lang/String java/lang/String java/lang/String] [java/lang/String java/lang/String]
    INVOKEDYNAMIC makeConcatWithConstants(Ljava/lang/String;Ljava/lang/String;)Ljava/lang/String; [
      // handle kind 0x6 : INVOKESTATIC
      java/lang/invoke/StringConcatFactory.makeConcatWithConstants(Ljava/lang/invoke/MethodHandles$Lookup;Ljava/lang/String;Ljava/lang/invoke/MethodType;Ljava/lang/String;[Ljava/lang/Object;)Ljava/lang/invoke/CallSite;
      // arguments:
      "\u0001\u0001"
    ]
    ASTORE 14
   L19
    LINENUMBER 33 L19
    ALOAD 14
    ALOAD 13
    LDC "1"
    INVOKEVIRTUAL java/lang/String.equals (Ljava/lang/Object;)Z
    IFNE L20
    ALOAD 13
    GOTO L21
   L20
   FRAME FULL [D D D D T T D java/lang/String java/lang/String java/lang/String] [java/lang/String]
    LDC ""
   L21
   FRAME FULL [D D D D T T D java/lang/String java/lang/String java/lang/String] [java/lang/String java/lang/String]
    INVOKEDYNAMIC makeConcatWithConstants(Ljava/lang/String;Ljava/lang/String;)Ljava/lang/String; [
      // handle kind 0x6 : INVOKESTATIC
      java/lang/invoke/StringConcatFactory.makeConcatWithConstants(Ljava/lang/invoke/MethodHandles$Lookup;Ljava/lang/String;Ljava/lang/invoke/MethodType;Ljava/lang/String;[Ljava/lang/Object;)Ljava/lang/invoke/CallSite;
      // arguments:
      "\u0001\u0001"
    ]
    ASTORE 14
   L22
    LINENUMBER 34 L22
    ALOAD 14
    INVOKEDYNAMIC makeConcatWithConstants(Ljava/lang/String;)Ljava/lang/String; [
      // handle kind 0x6 : INVOKESTATIC
      java/lang/invoke/StringConcatFactory.makeConcatWithConstants(Ljava/lang/invoke/MethodHandles$Lookup;Ljava/lang/String;Ljava/lang/invoke/MethodType;Ljava/lang/String;[Ljava/lang/Object;)Ljava/lang/invoke/CallSite;
      // arguments:
      "\u0001i"
    ]
    ASTORE 14
   L23
    LINENUMBER 35 L23
    GETSTATIC java/lang/System.out : Ljava/io/PrintStream;
    ALOAD 14
    INVOKEVIRTUAL java/io/PrintStream.println (Ljava/lang/String;)V
    GOTO L24
   L4
    LINENUMBER 37 L4
   FRAME FULL [D D D T T T T D] []
    DLOAD 10
    INVOKESTATIC qua/Quadratic.sqrtByNewton (D)D
    DSTORE 6
   L25
    LINENUMBER 39 L25
    LDC -0.5
    DLOAD 2
    DLOAD 2
    INVOKESTATIC qua/Quadratic.sign (D)I
    I2D
    DLOAD 6
    DMUL
    DADD
    DMUL
    DSTORE 8
   L26
    LINENUMBER 40 L26
    DLOAD 8
    DLOAD 0
    DDIV
    INVOKESTATIC qua/Quadratic.formatDouble (D)Ljava/lang/String;
    ASTORE 15
   L27
    LINENUMBER 41 L27
    DLOAD 4
    DLOAD 8
    DDIV
    INVOKESTATIC qua/Quadratic.formatDouble (D)Ljava/lang/String;
    ASTORE 16
   L28
    LINENUMBER 43 L28
    ALOAD 15
    INVOKEDYNAMIC makeConcatWithConstants(Ljava/lang/String;)Ljava/lang/String; [
      // handle kind 0x6 : INVOKESTATIC
      java/lang/invoke/StringConcatFactory.makeConcatWithConstants(Ljava/lang/invoke/MethodHandles$Lookup;Ljava/lang/String;Ljava/lang/invoke/MethodType;Ljava/lang/String;[Ljava/lang/Object;)Ljava/lang/invoke/CallSite;
      // arguments:
      "x1 = \u0001"
    ]
    ASTORE 14
   L29
    LINENUMBER 44 L29
    ALOAD 14
    ALOAD 15
    ALOAD 16
    INVOKEVIRTUAL java/lang/String.equals (Ljava/lang/Object;)Z
    IFNE L30
    ALOAD 16
    INVOKEDYNAMIC makeConcatWithConstants(Ljava/lang/String;)Ljava/lang/String; [
      // handle kind 0x6 : INVOKESTATIC
      java/lang/invoke/StringConcatFactory.makeConcatWithConstants(Ljava/lang/invoke/MethodHandles$Lookup;Ljava/lang/String;Ljava/lang/invoke/MethodType;Ljava/lang/String;[Ljava/lang/Object;)Ljava/lang/invoke/CallSite;
      // arguments:
      "\nx2 = \u0001"
    ]
    GOTO L31
   L30
   FRAME FULL [D D D D D D T T java/lang/String java/lang/String java/lang/String] [java/lang/String]
    LDC ""
   L31
   FRAME FULL [D D D D D D T T java/lang/String java/lang/String java/lang/String] [java/lang/String java/lang/String]
    INVOKEDYNAMIC makeConcatWithConstants(Ljava/lang/String;Ljava/lang/String;)Ljava/lang/String; [
      // handle kind 0x6 : INVOKESTATIC
      java/lang/invoke/StringConcatFactory.makeConcatWithConstants(Ljava/lang/invoke/MethodHandles$Lookup;Ljava/lang/String;Ljava/lang/invoke/MethodType;Ljava/lang/String;[Ljava/lang/Object;)Ljava/lang/invoke/CallSite;
      // arguments:
      "\u0001\u0001"
    ]
    ASTORE 14
   L32
    LINENUMBER 45 L32
    GETSTATIC java/lang/System.out : Ljava/io/PrintStream;
    ALOAD 14
    INVOKEVIRTUAL java/io/PrintStream.println (Ljava/lang/String;)V
   L24
    LINENUMBER 48 L24
   FRAME FULL [D D D D T T D T T java/lang/String] []
    RETURN
    MAXSTACK = 8
    MAXLOCALS = 17

  // access flags 0xA
  private static sign(D)I
   L0
    LINENUMBER 54 L0
    DLOAD 0
    DCONST_0
    DCMPL
    IFLE L1
    ICONST_1
    GOTO L2
   L1
   FRAME FULL [D] []
    ICONST_M1
   L2
   FRAME FULL [D] [I]
    IRETURN
    MAXSTACK = 4
    MAXLOCALS = 2

  // access flags 0xA
  private static sqrtByNewton(D)D
   L0
    LINENUMBER 63 L0
    DLOAD 0
    DCONST_0
    DCMPL
    IFNE L1
    DCONST_0
    DRETURN
   L1
    LINENUMBER 66 L1
   FRAME FULL [D] []
    DCONST_1
    DLOAD 0
    DADD
    LDC 2.0
    DDIV
    DSTORE 4
   L2
    LINENUMBER 70 L2
   FRAME FULL [D T T D] []
    DLOAD 4
    DLOAD 0
    DLOAD 4
    DDIV
    DADD
    LDC 2.0
    DDIV
    DSTORE 2
   L3
    LINENUMBER 71 L3
    DLOAD 4
    DLOAD 2
    DSUB
    LDC 1.0E-8
    DCMPG
    IFGE L4
   L5
    LINENUMBER 72 L5
    GOTO L6
   L4
    LINENUMBER 73 L4
   FRAME FULL [D D D] []
    DLOAD 2
    DSTORE 4
    GOTO L2
   L6
    LINENUMBER 76 L6
   FRAME FULL [D D D] []
    DLOAD 2
    DRETURN
    MAXSTACK = 6
    MAXLOCALS = 6

  // access flags 0xA
  private static formatDouble(D)Ljava/lang/String;
   L0
    LINENUMBER 86 L0
    DLOAD 0
    INVOKESTATIC java/lang/Math.floor (D)D
    DLOAD 0
    DCMPL
    IFNE L1
   L2
    LINENUMBER 87 L2
    DLOAD 0
    D2I
    INVOKESTATIC java/lang/Integer.valueOf (I)Ljava/lang/Integer;
    ASTORE 2
   L3
    LINENUMBER 88 L3
    ALOAD 2
    INVOKEVIRTUAL java/lang/Integer.toString ()Ljava/lang/String;
    ARETURN
   L1
    LINENUMBER 90 L1
   FRAME FULL [D] []
    DLOAD 0
    INVOKESTATIC java/lang/Double.valueOf (D)Ljava/lang/Double;
    ASTORE 2
   L4
    LINENUMBER 91 L4
    ALOAD 2
    INVOKEVIRTUAL java/lang/Double.toString ()Ljava/lang/String;
    ARETURN
    MAXSTACK = 4
    MAXLOCALS = 3

  // access flags 0x9
  public static validateInput(Ljava/lang/String;)D throws qua/NotEnoughPrecisionException 
   L0
    LINENUMBER 102 L0
    ALOAD 0
    INVOKESTATIC java/lang/Double.parseDouble (Ljava/lang/String;)D
    INVOKESTATIC java/lang/Double.valueOf (D)Ljava/lang/Double;
    ASTORE 1
   L1
    LINENUMBER 105 L1
    NEW java/text/DecimalFormat
    DUP
    LDC "###################################################################################################0.0###################################################################################################"
    INVOKESPECIAL java/text/DecimalFormat.<init> (Ljava/lang/String;)V
    ASTORE 2
   L2
    LINENUMBER 109 L2
    ALOAD 0
    ASTORE 3
   L3
    LINENUMBER 110 L3
    ALOAD 0
    BIPUSH 46
    INVOKEVIRTUAL java/lang/String.indexOf (I)I
    ICONST_M1
    IF_ICMPNE L4
    ALOAD 3
    INVOKEDYNAMIC makeConcatWithConstants(Ljava/lang/String;)Ljava/lang/String; [
      // handle kind 0x6 : INVOKESTATIC
      java/lang/invoke/StringConcatFactory.makeConcatWithConstants(Ljava/lang/invoke/MethodHandles$Lookup;Ljava/lang/String;Ljava/lang/invoke/MethodType;Ljava/lang/String;[Ljava/lang/Object;)Ljava/lang/invoke/CallSite;
      // arguments:
      "\u0001.0"
    ]
    ASTORE 3
   L4
    LINENUMBER 113 L4
   FRAME FULL [java/lang/String java/lang/Double java/text/DecimalFormat java/lang/String] []
    ALOAD 2
    ALOAD 1
    INVOKEVIRTUAL java/text/DecimalFormat.format (Ljava/lang/Object;)Ljava/lang/String;
    ALOAD 3
    INVOKEVIRTUAL java/lang/String.equals (Ljava/lang/Object;)Z
    IFNE L5
    ALOAD 1
    INVOKEVIRTUAL java/lang/Double.toString ()Ljava/lang/String;
    ALOAD 0
    INVOKEVIRTUAL java/lang/String.equals (Ljava/lang/Object;)Z
    IFNE L5
   L6
    LINENUMBER 114 L6
    NEW qua/NotEnoughPrecisionException
    DUP
    INVOKESPECIAL qua/NotEnoughPrecisionException.<init> ()V
    ATHROW
   L5
    LINENUMBER 116 L5
   FRAME FULL [java/lang/String java/lang/Double java/text/DecimalFormat java/lang/String] []
    ALOAD 1
    INVOKEVIRTUAL java/lang/Double.doubleValue ()D
    DRETURN
    MAXSTACK = 3
    MAXLOCALS = 4

  // access flags 0x9
  public static main([Ljava/lang/String;)V
    TRYCATCHBLOCK L0 L1 L2 qua/NotEnoughPrecisionException
    TRYCATCHBLOCK L3 L4 L2 qua/NotEnoughPrecisionException
    TRYCATCHBLOCK L0 L1 L5 java/lang/NumberFormatException
    TRYCATCHBLOCK L3 L4 L5 java/lang/NumberFormatException
    TRYCATCHBLOCK L6 L7 L8 qua/NotEnoughPrecisionException
   L9
    LINENUMBER 123 L9
    DCONST_0
    DUP2
    DSTORE 5
    DUP2
    DSTORE 3
    DSTORE 1
   L10
    LINENUMBER 128 L10
    GETSTATIC java/lang/System.out : Ljava/io/PrintStream;
    LDC "Welcome to Quadratic Equation Solver.\nA quadratic equation can be written in the form ax^2 + bx + c = 0, where x is an unknown, a, b, and c are constants, and a is not zero.\nGiven values for a, b, and c, this program will produce the two roots of the equation. Both real and complex roots are supported, but not complex coefficients.\nPress Ctrl+C to quit at any time."
    INVOKEVIRTUAL java/io/PrintStream.println (Ljava/lang/String;)V
   L11
    LINENUMBER 133 L11
    NEW java/util/Scanner
    DUP
    GETSTATIC java/lang/System.in : Ljava/io/InputStream;
    INVOKESPECIAL java/util/Scanner.<init> (Ljava/io/InputStream;)V
    ASTORE 8
   L0
    LINENUMBER 140 L0
   FRAME FULL [[Ljava/lang/String; D D D T java/util/Scanner] []
    GETSTATIC java/lang/System.out : Ljava/io/PrintStream;
    LDC "Enter a value for 'a':"
    INVOKEVIRTUAL java/io/PrintStream.println (Ljava/lang/String;)V
   L12
    LINENUMBER 141 L12
    ALOAD 8
    INVOKEVIRTUAL java/util/Scanner.next ()Ljava/lang/String;
    INVOKESTATIC qua/Quadratic.validateInput (Ljava/lang/String;)D
    DSTORE 1
   L13
    LINENUMBER 143 L13
    DLOAD 1
    DCONST_0
    DCMPL
    IFNE L3
   L14
    LINENUMBER 144 L14
    GETSTATIC java/lang/System.out : Ljava/io/PrintStream;
    LDC "'a' cannot be zero!"
    POP
    POP
   L1
    LINENUMBER 145 L1
    GOTO L0
   L3
    LINENUMBER 147 L3
   FRAME FULL [[Ljava/lang/String; D D D T java/util/Scanner] []
    GETSTATIC java/lang/System.out : Ljava/io/PrintStream;
    LDC "Enter a value for 'b':"
    INVOKEVIRTUAL java/io/PrintStream.println (Ljava/lang/String;)V
   L15
    LINENUMBER 148 L15
    ALOAD 8
    INVOKEVIRTUAL java/util/Scanner.next ()Ljava/lang/String;
    INVOKESTATIC qua/Quadratic.validateInput (Ljava/lang/String;)D
    DSTORE 3
   L16
    LINENUMBER 149 L16
    GETSTATIC java/lang/System.out : Ljava/io/PrintStream;
    LDC "Enter a value for 'c':"
    INVOKEVIRTUAL java/io/PrintStream.println (Ljava/lang/String;)V
   L17
    LINENUMBER 150 L17
    ALOAD 8
    INVOKEVIRTUAL java/util/Scanner.next ()Ljava/lang/String;
    INVOKESTATIC qua/Quadratic.validateInput (Ljava/lang/String;)D
    DSTORE 5
   L4
    LINENUMBER 158 L4
    GOTO L6
   L2
    LINENUMBER 151 L2
   FRAME FULL [[Ljava/lang/String; D D D T java/util/Scanner] [qua/NotEnoughPrecisionException]
    ASTORE 9
   L18
    LINENUMBER 152 L18
    GETSTATIC java/lang/System.out : Ljava/io/PrintStream;
    LDC "The value you entered is too large or too small! Please enter a value between 4.9E-324 and 1.7976931348623157E308."
    INVOKEVIRTUAL java/io/PrintStream.println (Ljava/lang/String;)V
   L19
    LINENUMBER 154 L19
    GOTO L0
   L5
    LINENUMBER 155 L5
   FRAME FULL [[Ljava/lang/String; D D D T java/util/Scanner] [java/lang/NumberFormatException]
    ASTORE 9
   L20
    LINENUMBER 156 L20
    GETSTATIC java/lang/System.out : Ljava/io/PrintStream;
    LDC "The value you entered is not allowed! Please enter a number. E.g. 4, 0.3, -12"
    INVOKEVIRTUAL java/io/PrintStream.println (Ljava/lang/String;)V
   L21
    LINENUMBER 157 L21
    GOTO L0
   L6
    LINENUMBER 162 L6
   FRAME FULL [[Ljava/lang/String; D D D T java/util/Scanner] []
    DLOAD 1
    DLOAD 3
    DLOAD 5
    INVOKESTATIC qua/Quadratic.solveQuadratic (DDD)V
   L7
    LINENUMBER 166 L7
    GOTO L22
   L8
    LINENUMBER 163 L8
   FRAME FULL [[Ljava/lang/String; D D D T java/util/Scanner] [qua/NotEnoughPrecisionException]
    ASTORE 9
   L23
    LINENUMBER 164 L23
    GETSTATIC java/lang/System.out : Ljava/io/PrintStream;
    LDC "Failed to find an accurate solution! This can happen when the values are too big, a is too close to zero, or b^2 is much bigger than 4ac."
    INVOKEVIRTUAL java/io/PrintStream.println (Ljava/lang/String;)V
   L22
    LINENUMBER 169 L22
   FRAME FULL [[Ljava/lang/String; D D D T java/util/Scanner] []
    GETSTATIC java/lang/System.out : Ljava/io/PrintStream;
    LDC "Would you like to try again? [y/n]"
    INVOKEVIRTUAL java/io/PrintStream.println (Ljava/lang/String;)V
   L24
    LINENUMBER 170 L24
    ALOAD 8
    INVOKEVIRTUAL java/util/Scanner.next ()Ljava/lang/String;
    ASTORE 7
   L25
    LINENUMBER 173 L25
    ALOAD 7
    LDC "y"
    INVOKEVIRTUAL java/lang/String.equals (Ljava/lang/Object;)Z
    IFNE L0
   L26
    LINENUMBER 174 L26
    GOTO L27
   L27
    LINENUMBER 179 L27
   FRAME FULL [[Ljava/lang/String; D D D java/lang/String java/util/Scanner] []
    GETSTATIC java/lang/System.out : Ljava/io/PrintStream;
    LDC "Thank you for using Quadratic Equation Solver!"
    INVOKEVIRTUAL java/io/PrintStream.println (Ljava/lang/String;)V
   L28
    LINENUMBER 181 L28
    RETURN
    MAXSTACK = 6
    MAXLOCALS = 10
}

